testframework/__init__.py
testframework/fixtures.py
testframework/checkers/__init__.py
testframework/checkers/bigquery_checker.py
testframework/checkers/bigquery_client_checker.py
testframework/checkers/bigquery_table_checker.py
testframework/checkers/bigtable_checker.py
testframework/checkers/bigtable_instance_checker.py
testframework/checkers/bigtable_matchers.py
testframework/checkers/checker_message.py
testframework/checkers/checker_message_factory.py
testframework/checkers/pubsub_client_checker.py
testframework/checkers/pubsub_message.py
testframework/checkers/pubsub_message_receiver.py
testframework/checkers/pubsub_publisher.py
testframework/checkers/pubsub_topic_checker.py
testframework/checkers/pubsub_topic_matchers.py
testframework/checkers/spanner_checker.py
testframework/config/__init__.py
testframework/config/environment.py
testframework/exceptions/__init__.py
testframework/exceptions/pubsub_checker_error.py
testframework/exceptions/pubsub_creator_error.py
testframework/inserter/__init__.py
testframework/inserter/bigtable_inserter.py
testframework/pubsub/__init__.py
testframework/pubsub/pubsub_checker.py
testframework/pubsub/pubsub_creator.py
testframework/util/__init__.py
testframework/util/assertion.py
testframework/util/date_generator.py
testframework/util/sql_handler.py
tests/checkers/__init__.py
tests/checkers/test_bigquery_checker.py
tests/checkers/test_bigquery_table_checker.py
tests/checkers/test_bigtable_checker.py
tests/checkers/test_checker_message.py
tests/checkers/test_checker_message_factory.py
tests/checkers/test_pubsub_client_checker.py
tests/checkers/test_pubsub_message_receiver.py
tests/checkers/test_pubsub_publisher.py
tests/checkers/test_pubsub_topic_checker.py
tests/checkers/test_spanner_checker.py
tests/inserter/__init__.py
tests/inserter/test_bigtable_inserter.py
tests/pubsub/__init__.py
tests/pubsub/test_pubsub_checker.py
tests/pubsub/test_pubsub_creator.py
tests/util/__init__.py
tests/util/dummy_decorator.py
ems_dataflow_testframework-1.2.5.dist-info/LICENSE
ems_dataflow_testframework-1.2.5.dist-info/METADATA
ems_dataflow_testframework-1.2.5.dist-info/WHEEL
ems_dataflow_testframework-1.2.5.dist-info/top_level.txt
ems_dataflow_testframework-1.2.5.dist-info/RECORD
