Metadata-Version: 2.1
Name: ems-dataflow-testframework
Version: 1.2.5
Summary: Framework helping testing Google Cloud Dataflows
Home-page: UNKNOWN
Author: Emarsys
License: UNKNOWN
Platform: UNKNOWN
Classifier: Programming Language :: Python :: 3
Classifier: License :: OSI Approved :: MIT License
Classifier: Operating System :: OS Independent
Requires-Dist: atomicwrites (==1.3.0)
Requires-Dist: attrs (==19.1.0)
Requires-Dist: cachetools (==3.1.1)
Requires-Dist: certifi (==2019.6.16)
Requires-Dist: chardet (==3.0.4)
Requires-Dist: ems-gcp-toolkit (==0.1.76)
Requires-Dist: google-auth (==1.6.3)
Requires-Dist: google-cloud-bigtable (==1.0.0)
Requires-Dist: google-resumable-media (==0.4.0)
Requires-Dist: grpcio (==1.23.0)
Requires-Dist: idna (==2.8)
Requires-Dist: importlib-metadata (==0.21)
Requires-Dist: inflection (==0.3.1)
Requires-Dist: more-itertools (==7.2.0)
Requires-Dist: packaging (==19.1)
Requires-Dist: pluggy (==0.13.0)
Requires-Dist: protobuf (==3.9.1)
Requires-Dist: py (==1.8.0)
Requires-Dist: pyasn1 (==0.4.7)
Requires-Dist: pyasn1-modules (==0.2.6)
Requires-Dist: pyparsing (==2.4.2)
Requires-Dist: pytest (==5.1.2)
Requires-Dist: pytz (==2019.2)
Requires-Dist: requests (==2.22.0)
Requires-Dist: rsa (==4.0)
Requires-Dist: six (==1.12.0)
Requires-Dist: tenacity (==5.1.1)
Requires-Dist: urllib3 (==1.25.3)
Requires-Dist: wcwidth (==0.1.7)
Requires-Dist: zipp (==0.6.0)
